{
  "ABIRoot": {
    "kind": "Root",
    "name": "TopLevel",
    "printedName": "TopLevel",
    "children": [
      {
        "kind": "Import",
        "name": "Foundation",
        "printedName": "Foundation",
        "declKind": "Import",
        "moduleName": "Maths",
        "declAttributes": [
          "RawDocComment"
        ]
      },
      {
        "kind": "TypeDecl",
        "name": "Operations",
        "printedName": "Operations",
        "children": [
          {
            "kind": "Function",
            "name": "addNumbers",
            "printedName": "addNumbers(num1:num2:)",
            "children": [
              {
                "kind": "TypeNominal",
                "name": "Double",
                "printedName": "Swift.Double",
                "usr": "s:Sd"
              },
              {
                "kind": "TypeNominal",
                "name": "Double",
                "printedName": "Swift.Double",
                "usr": "s:Sd"
              },
              {
                "kind": "TypeNominal",
                "name": "Double",
                "printedName": "Swift.Double",
                "usr": "s:Sd"
              }
            ],
            "declKind": "Func",
            "usr": "s:5Maths10OperationsV10addNumbers4num14num2S2d_SdtFZ",
            "mangledName": "$s5Maths10OperationsV10addNumbers4num14num2S2d_SdtFZ",
            "moduleName": "Maths",
            "static": true,
            "declAttributes": [
              "AccessControl"
            ],
            "funcSelfKind": "NonMutating"
          },
          {
            "kind": "Function",
            "name": "subtractNumbers",
            "printedName": "subtractNumbers(num1:num2:)",
            "children": [
              {
                "kind": "TypeNominal",
                "name": "Double",
                "printedName": "Swift.Double",
                "usr": "s:Sd"
              },
              {
                "kind": "TypeNominal",
                "name": "Double",
                "printedName": "Swift.Double",
                "usr": "s:Sd"
              },
              {
                "kind": "TypeNominal",
                "name": "Double",
                "printedName": "Swift.Double",
                "usr": "s:Sd"
              }
            ],
            "declKind": "Func",
            "usr": "s:5Maths10OperationsV15subtractNumbers4num14num2S2d_SdtFZ",
            "mangledName": "$s5Maths10OperationsV15subtractNumbers4num14num2S2d_SdtFZ",
            "moduleName": "Maths",
            "static": true,
            "declAttributes": [
              "AccessControl"
            ],
            "funcSelfKind": "NonMutating"
          },
          {
            "kind": "Function",
            "name": "multiplyNumbers",
            "printedName": "multiplyNumbers(num1:num2:)",
            "children": [
              {
                "kind": "TypeNominal",
                "name": "Double",
                "printedName": "Swift.Double",
                "usr": "s:Sd"
              },
              {
                "kind": "TypeNominal",
                "name": "Double",
                "printedName": "Swift.Double",
                "usr": "s:Sd"
              },
              {
                "kind": "TypeNominal",
                "name": "Double",
                "printedName": "Swift.Double",
                "usr": "s:Sd"
              }
            ],
            "declKind": "Func",
            "usr": "s:5Maths10OperationsV15multiplyNumbers4num14num2S2d_SdtFZ",
            "mangledName": "$s5Maths10OperationsV15multiplyNumbers4num14num2S2d_SdtFZ",
            "moduleName": "Maths",
            "static": true,
            "declAttributes": [
              "AccessControl"
            ],
            "funcSelfKind": "NonMutating"
          },
          {
            "kind": "Function",
            "name": "divideNumbers",
            "printedName": "divideNumbers(num1:num2:)",
            "children": [
              {
                "kind": "TypeNominal",
                "name": "Double",
                "printedName": "Swift.Double",
                "usr": "s:Sd"
              },
              {
                "kind": "TypeNominal",
                "name": "Double",
                "printedName": "Swift.Double",
                "usr": "s:Sd"
              },
              {
                "kind": "TypeNominal",
                "name": "Double",
                "printedName": "Swift.Double",
                "usr": "s:Sd"
              }
            ],
            "declKind": "Func",
            "usr": "s:5Maths10OperationsV13divideNumbers4num14num2S2d_SdtFZ",
            "mangledName": "$s5Maths10OperationsV13divideNumbers4num14num2S2d_SdtFZ",
            "moduleName": "Maths",
            "static": true,
            "declAttributes": [
              "AccessControl"
            ],
            "funcSelfKind": "NonMutating"
          },
          {
            "kind": "Function",
            "name": "squareRoot",
            "printedName": "squareRoot(of:)",
            "children": [
              {
                "kind": "TypeNominal",
                "name": "Double",
                "printedName": "Swift.Double",
                "usr": "s:Sd"
              },
              {
                "kind": "TypeNominal",
                "name": "Double",
                "printedName": "Swift.Double",
                "usr": "s:Sd"
              }
            ],
            "declKind": "Func",
            "usr": "s:5Maths10OperationsV10squareRoot2ofS2d_tFZ",
            "mangledName": "$s5Maths10OperationsV10squareRoot2ofS2d_tFZ",
            "moduleName": "Maths",
            "static": true,
            "declAttributes": [
              "AccessControl"
            ],
            "funcSelfKind": "NonMutating"
          }
        ],
        "declKind": "Struct",
        "usr": "s:5Maths10OperationsV",
        "mangledName": "$s5Maths10OperationsV",
        "moduleName": "Maths",
        "declAttributes": [
          "AccessControl"
        ]
      }
    ],
    "json_format_version": 8
  },
  "ConstValues": []
}